CHANGES
LICENSE
README.txt
setup.py
iw/__init__.py
iw.cache.egg-info/PKG-INFO
iw.cache.egg-info/SOURCES.txt
iw.cache.egg-info/dependency_links.txt
iw.cache.egg-info/entry_points.txt
iw.cache.egg-info/namespace_packages.txt
iw.cache.egg-info/not-zip-safe
iw.cache.egg-info/requires.txt
iw.cache.egg-info/top_level.txt
iw/cache/README.txt
iw/cache/__init__.py
iw/cache/configure.zcml
iw/cache/decorators.py
iw/cache/interfaces.py
iw/cache/keys.py
iw/cache/memcached.py
iw/cache/meta.zcml
iw/cache/metaconfigure.py
iw/cache/metadirectives.py
iw/cache/ramcache.py
iw/cache/testing.py
iw/cache/utils.py
iw/cache/docs/README.txt
iw/cache/doctests/README.txt
iw/cache/doctests/memcache.txt
iw/cache/doctests/ramcache.txt
iw/cache/tests/__init__.py
iw/cache/tests/servers.zcml
iw/cache/tests/test_cachedocs.py
iw/cache/tests/test_cachedocstrings.py
