Metadata-Version: 1.0
Name: iw.cache
Version: 0.1
Summary: code-level helpers for caching
Home-page: UNKNOWN
Author: Ingeniweb
Author-email: support@ingeniweb.com
License: GPL
Keywords: cache
Platform: UNKNOWN
Classifier: Programming Language :: Python
Classifier: Topic :: Software Development :: Libraries :: Python Modules
